{
  "version": "6",
  "dialect": "sqlite",
  "id": "189e1282-ff32-497d-b6a3-f8c8e931ad50",
  "prevId": "37e2146b-bb55-47d1-ba5c-078910c8ee34",
  "tables": {
    "files": {
      "name": "files",
      "columns": {
        "id": {
          "name": "id",
          "type": "integer",
          "primaryKey": true,
          "notNull": true,
          "autoincrement": true
        },
        "path": {
          "name": "path",
          "type": "text",
          "primaryKey": false,
          "notNull": true,
          "autoincrement": false
        },
        "dir": {
          "name": "dir",
          "type": "text",
          "primaryKey": false,
          "notNull": true,
          "autoincrement": false
        },
        "name": {
          "name": "name",
          "type": "text",
          "primaryKey": false,
          "notNull": true,
          "autoincrement": false
        },
        "ext": {
          "name": "ext",
          "type": "text",
          "primaryKey": false,
          "notNull": true,
          "autoincrement": false
        },
        "size": {
          "name": "size",
          "type": "integer",
          "primaryKey": false,
          "notNull": true,
          "autoincrement": false
        },
        "mtime": {
          "name": "mtime",
          "type": "integer",
          "primaryKey": false,
          "notNull": true,
          "autoincrement": false
        },
        "ctime": {
          "name": "ctime",
          "type": "integer",
          "primaryKey": false,
          "notNull": true,
          "autoincrement": false
        },
        "width": {
          "name": "width",
          "type": "integer",
          "primaryKey": false,
          "notNull": false,
          "autoincrement": false
        },
        "height": {
          "name": "height",
          "type": "integer",
          "primaryKey": false,
          "notNull": false,
          "autoincrement": false
        },
        "duration": {
          "name": "duration",
          "type": "real",
          "primaryKey": false,
          "notNull": false,
          "autoincrement": false
        },
        "lat": {
          "name": "lat",
          "type": "real",
          "primaryKey": false,
          "notNull": false,
          "autoincrement": false
        },
        "lon": {
          "name": "lon",
          "type": "real",
          "primaryKey": false,
          "notNull": false,
          "autoincrement": false
        },
        "taken_at": {
          "name": "taken_at",
          "type": "text",
          "primaryKey": false,
          "notNull": false,
          "autoincrement": false
        },
        "xmp_path": {
          "name": "xmp_path",
          "type": "text",
          "primaryKey": false,
          "notNull": false,
          "autoincrement": false
        },
        "xmp_mtime": {
          "name": "xmp_mtime",
          "type": "integer",
          "primaryKey": false,
          "notNull": false,
          "autoincrement": false
        },
        "last_indexed_at": {
          "name": "last_indexed_at",
          "type": "text",
          "primaryKey": false,
          "notNull": false,
          "autoincrement": false
        }
      },
      "indexes": {
        "files_path_unique": {
          "name": "files_path_unique",
          "columns": [
            "path"
          ],
          "isUnique": true
        },
        "files_dir_idx": {
          "name": "files_dir_idx",
          "columns": [
            "dir"
          ],
          "isUnique": false
        },
        "files_ext_name_idx": {
          "name": "files_ext_name_idx",
          "columns": [
            "ext",
            "name"
          ],
          "isUnique": false
        },
        "files_taken_at_idx": {
          "name": "files_taken_at_idx",
          "columns": [
            "taken_at"
          ],
          "isUnique": false
        },
        "files_mtime_idx": {
          "name": "files_mtime_idx",
          "columns": [
            "mtime"
          ],
          "isUnique": false
        },
        "files_size_idx": {
          "name": "files_size_idx",
          "columns": [
            "size"
          ],
          "isUnique": false
        }
      },
      "foreignKeys": {},
      "compositePrimaryKeys": {},
      "uniqueConstraints": {}
    },
    "file_tags": {
      "name": "file_tags",
      "columns": {
        "file_id": {
          "name": "file_id",
          "type": "integer",
          "primaryKey": false,
          "notNull": true,
          "autoincrement": false
        },
        "tag_id": {
          "name": "tag_id",
          "type": "integer",
          "primaryKey": false,
          "notNull": true,
          "autoincrement": false
        }
      },
      "indexes": {
        "ft_tag_file_idx": {
          "name": "ft_tag_file_idx",
          "columns": [
            "tag_id",
            "file_id"
          ],
          "isUnique": false
        }
      },
      "foreignKeys": {
        "file_tags_file_id_files_id_fk": {
          "name": "file_tags_file_id_files_id_fk",
          "tableFrom": "file_tags",
          "tableTo": "files",
          "columnsFrom": [
            "file_id"
          ],
          "columnsTo": [
            "id"
          ],
          "onDelete": "cascade",
          "onUpdate": "no action"
        },
        "file_tags_tag_id_tags_id_fk": {
          "name": "file_tags_tag_id_tags_id_fk",
          "tableFrom": "file_tags",
          "tableTo": "tags",
          "columnsFrom": [
            "tag_id"
          ],
          "columnsTo": [
            "id"
          ],
          "onDelete": "cascade",
          "onUpdate": "no action"
        }
      },
      "compositePrimaryKeys": {
        "file_tags_pk": {
          "columns": [
            "file_id",
            "tag_id"
          ],
          "name": "file_tags_pk"
        }
      },
      "uniqueConstraints": {}
    },
    "tags": {
      "name": "tags",
      "columns": {
        "id": {
          "name": "id",
          "type": "integer",
          "primaryKey": true,
          "notNull": true,
          "autoincrement": true
        },
        "name": {
          "name": "name",
          "type": "text",
          "primaryKey": false,
          "notNull": true,
          "autoincrement": false
        },
        "slug": {
          "name": "slug",
          "type": "text",
          "primaryKey": false,
          "notNull": true,
          "autoincrement": false
        },
        "color": {
          "name": "color",
          "type": "text",
          "primaryKey": false,
          "notNull": false,
          "autoincrement": false
        },
        "group": {
          "name": "group",
          "type": "text",
          "primaryKey": false,
          "notNull": false,
          "autoincrement": false
        },
        "parent_id": {
          "name": "parent_id",
          "type": "integer",
          "primaryKey": false,
          "notNull": false,
          "autoincrement": false
        },
        "source": {
          "name": "source",
          "type": "text",
          "primaryKey": false,
          "notNull": true,
          "autoincrement": false
        }
      },
      "indexes": {
        "tags_slug_unique": {
          "name": "tags_slug_unique",
          "columns": [
            "slug"
          ],
          "isUnique": true
        },
        "tags_parent_idx": {
          "name": "tags_parent_idx",
          "columns": [
            "parent_id"
          ],
          "isUnique": false
        }
      },
      "foreignKeys": {},
      "compositePrimaryKeys": {},
      "uniqueConstraints": {}
    },
    "sources": {
      "name": "sources",
      "columns": {
        "id": {
          "name": "id",
          "type": "integer",
          "primaryKey": true,
          "notNull": true,
          "autoincrement": true
        },
        "signature": {
          "name": "signature",
          "type": "text",
          "primaryKey": false,
          "notNull": true,
          "autoincrement": false
        },
        "roots_json": {
          "name": "roots_json",
          "type": "text",
          "primaryKey": false,
          "notNull": true,
          "autoincrement": false
        },
        "last_scanned_at": {
          "name": "last_scanned_at",
          "type": "text",
          "primaryKey": false,
          "notNull": false,
          "autoincrement": false
        }
      },
      "indexes": {
        "sources_signature_unique": {
          "name": "sources_signature_unique",
          "columns": [
            "signature"
          ],
          "isUnique": true
        }
      },
      "foreignKeys": {},
      "compositePrimaryKeys": {},
      "uniqueConstraints": {}
    }
  },
  "enums": {},
  "_meta": {
    "schemas": {},
    "tables": {},
    "columns": {}
  },
  "internal": {
    "indexes": {}
  }
}